ml_simple_gui/__init__.py
ml_simple_gui/utils.py
ml_simple_gui/frontend/dist/favicon.ico
ml_simple_gui/frontend/dist/index.html
ml_simple_gui/frontend/dist/css/chunk-vendors.6a84c9a3.css
ml_simple_gui/frontend/dist/js/app.b230bd4f.js
ml_simple_gui/frontend/dist/js/app.b230bd4f.js.map
ml_simple_gui/frontend/dist/js/chunk-vendors.4d341bce.js
ml_simple_gui/frontend/dist/js/chunk-vendors.4d341bce.js.map
ml_simple_gui-1.0.6.dist-info/METADATA
ml_simple_gui-1.0.6.dist-info/WHEEL
ml_simple_gui-1.0.6.dist-info/top_level.txt
ml_simple_gui-1.0.6.dist-info/RECORD
