Metadata-Version: 2.1
Name: ml-simple-gui
Version: 1.0.6
Summary: UNKNOWN
Home-page: UNKNOWN
License: UNKNOWN
Platform: UNKNOWN
Requires-Dist: click (==8.0.1)
Requires-Dist: colorama (==0.4.4)
Requires-Dist: Flask (==2.0.1)
Requires-Dist: Flask-Cors (==3.0.10)
Requires-Dist: importlib-metadata (==4.3.0)
Requires-Dist: itsdangerous (==2.0.1)
Requires-Dist: Jinja2 (==3.0.1)
Requires-Dist: joblib (==1.0.1)
Requires-Dist: MarkupSafe (==2.0.1)
Requires-Dist: numpy (==1.21.0)
Requires-Dist: pandas (==1.2.5)
Requires-Dist: python-dateutil (==2.8.1)
Requires-Dist: pytz (==2021.1)
Requires-Dist: scikit-learn (==0.24.2)
Requires-Dist: scipy (==1.7.0)
Requires-Dist: six (==1.16.0)
Requires-Dist: threadpoolctl (==2.1.0)
Requires-Dist: typing-extensions (==3.10.0.0)
Requires-Dist: Werkzeug (==2.0.1)
Requires-Dist: zipp (==3.4.1)
